correpondence_annotator/__init__.py
correpondence_annotator/_nbdev.py
correpondence_annotator/core.py
pixelstitch/__init__.py
pixelstitch/_nbdev.py
pixelstitch/core.py
pixelstitch/deephelp.py
pixelstitch/deephelper.py
pixelstitch/imgproc.py
pixelstitch/io.py
pixelstitch/metrics.py
pixelstitch-0.1.5.dist-info/LICENSE
pixelstitch-0.1.5.dist-info/METADATA
pixelstitch-0.1.5.dist-info/WHEEL
pixelstitch-0.1.5.dist-info/top_level.txt
pixelstitch-0.1.5.dist-info/RECORD
