Metadata-Version: 2.1
Name: pixelstitch
Version: 0.1.5
Summary: Matplotlib-based tool for labeling the two-view correspondences
Home-page: https://github.com/ducha-aiki/pixelstitch/tree/master/
Author: Dmytro Mishkin
Author-email: ducha.aiki@gmail.com
License: Apache Software License 2.0
Keywords: local features,correspondences,RANSAC,image matching,WBS,WxBS
Classifier: Development Status :: 3 - Alpha
Classifier: Intended Audience :: Developers
Classifier: Natural Language :: English
Classifier: Programming Language :: Python :: 3.8
Classifier: License :: OSI Approved :: Apache Software License
Requires-Python: >=3.8
License-File: LICENSE
Requires-Dist: pip
Requires-Dist: packaging
Requires-Dist: matplotlib <3.5
Requires-Dist: kornia-moons
Requires-Dist: kornia >=0.5.10
Requires-Dist: numpy <2
Provides-Extra: dev
